Metadata-Version: 2.1
Name: oneNeuron-pypi-shreelatha
Version: 0.0.3
Summary: It's an implementation of perceptron
Home-page: https://github.com/shreelatha/oneNeuron_pypi
Author: shreelatha
Author-email: shreelathan@gmail.com
License: UNKNOWN
Project-URL: Bug Tracker, https://github.com/shreelatha/oneNeuron_pypi/issues
Platform: UNKNOWN
Classifier: Programming Language :: Python :: 3
Classifier: License :: OSI Approved :: MIT License
Classifier: Operating System :: OS Independent
Requires-Python: >=3.6
License-File: LICENSE
Requires-Dist: numpy
Requires-Dist: tqdm
